{
  "status": "ok",
  "doc_id": "WOdodZ81zoAfXExOThplFWaQgyb",
  "url": "https://congdongagi.sg.larksuite.com/wiki/OUOwwDb6vifqsxkFt7ClUItYg9e",
  "title": "Hạn chót 25/3 | Tổng giải thưởng trị giá 500.000 NDT, tìm kiếm \"Tôm hùm\" cấp ngành!",
  "revision": 141,
  "total_blocks": 137,
  "translatable_blocks": 92,
  "blocks": [
    {
      "block_id": "WOdodZ81zoAfXExOThplFWaQgyb",
      "block_type": 1,
      "block_type_name": "page",
      "elements": [
        {
          "type": "text_run",
          "content": "Hạn chót 25/3 | Tổng giải thưởng trị giá 500.000 NDT, tìm kiếm \"Tôm hùm\" cấp ngành!",
          "style": {
            "bold": false,
            "inline_code": false,
            "italic": false,
            "strikethrough": false,
            "underline": false
          }
        }
      ]
    },
    {
      "block_id": "doxlgZcLofvwugBZuX6Miu2S4Pd",
      "block_type": 15,
      "block_type_name": "quote",
      "elements": [
        {
          "type": "text_run",
          "content": "🔗 Link bài gốc: ",
          "style": {
            "bold": false,
            "inline_code": false,
            "italic": false,
            "strikethrough": false,
            "underline": false
          }
        },
        {
          "type": "text_run",
          "content": "https://mp.weixin.qq.com/s/IeftLs5l...",
          "style": {
            "bold": false,
            "inline_code": false,
            "italic": false,
            "link": {
              "url": "https%3A%2F%2Fmp.weixin.qq.com%2Fs%2FIeftLs5ljq5Wu4kcFfOHCA"
            },
            "strikethrough": false,
            "underline": false
          }
        }
      ]
    },
    {
      "block_id": "doxlgxmIpvGOTQBPpvw9Lx2e7TS",
      "block_type": 2,
      "block_type_name": "text",
      "elements": [
        {
          "type": "text_run",
          "content": "Bài gốc: Linh Tiểu Hạch - Linh Hạch Số Trí",
          "style": {
            "bold": false,
            "inline_code": false,
            "italic": false,
            "strikethrough": false,
            "underline": false
          }
        },
        {
          "type": "text_run",
          "content": "16/03/2026 17:32  Chiết Giang",
          "style": {
            "bold": false,
            "inline_code": false,
            "italic": true,
            "strikethrough": false,
            "underline": false
          }
        }
      ]
    },
    {
      "block_id": "doxlgKrcKilmTT9XMiu9MUOPL7g",
      "block_type": 2,
      "block_type_name": "text",
      "elements": [
        {
          "type": "text_run",
          "content": "Trong năm qua, các nhà phát triển toàn cầu đang điên cuồng khám phá các khả năng của Agent: nghiên cứu tự động, giao dịch tự động, vận hành tự động, chăm sóc khách hàng tự động, phát triển tự động, ra quyết định tự động... nhưng các Agent thực sự có thể ứng dụng vào ngành vẫn rất ít. Phần lớn Agent vẫn dừng lại ở giai đoạn chatbot hoặc ứng dụng giải trí.",
          "style": {
            "bold": false,
            "inline_code": false,
            "italic": false,
            "strikethrough": false,
            "underline": false
          }
        }
      ]
    },
    {
      "block_id": "doxlghJIk15gkqEuw3PsoDz7I6g",
      "block_type": 2,
      "block_type_name": "text",
      "elements": [
        {
          "type": "text_run",
          "content": "Làn sóng khởi nghiệp AI tiếp theo sẽ sinh ra một hình thái sản phẩm hoàn toàn mới: Agent cấp ngành. Chúng sẽ đi sâu vào y tế, tài chính, sản xuất, giáo dục, pháp luật, dịch vụ doanh nghiệp và nhiều kịch bản thực tế khác, trở thành các tác tử thông minh có khả năng giải quyết vấn đề thực, tạo ra giá trị thực, mang lại cơ hội kinh doanh thực, chuyển từ \"ứng dụng đồ chơi\" thành công cụ năng suất cấp công nghiệp thực sự.",
          "style": {
            "bold": false,
            "inline_code": false,
            "italic": false,
            "strikethrough": false,
            "underline": false
          }
        }
      ]
    },
    {
      "block_id": "doxlgf04bjqi60dVeWlxAuyXHeh",
      "block_type": 2,
      "block_type_name": "text",
      "elements": [
        {
          "type": "text_run",
          "content": "Vì vậy, Linh Hạch Số Trí phối hợp cùng ",
          "style": {
            "bold": false,
            "inline_code": false,
            "italic": false,
            "strikethrough": false,
            "underline": false
          }
        },
        {
          "type": "text_run",
          "content": "Thiên Tế Khoa Kỹ Đầu Tư, Vi Liên, Phi Phàm Sản Nghiên ",
          "style": {
            "bold": true,
            "inline_code": false,
            "italic": false,
            "strikethrough": false,
            "underline": false
          }
        },
        {
          "type": "text_run",
          "content": ", Qianwen và các doanh nghiệp, tổ chức khác phát động sự kiện lớn này —— ",
          "style": {
            "bold": false,
            "inline_code": false,
            "italic": false,
            "strikethrough": false,
            "underline": false
          }
        },
        {
          "type": "text_run",
          "content": "AI Hackathon Tôm Hùm · Cuộc thi Bình chọn Agent cấp ngành ",
          "style": {
            "bold": true,
            "inline_code": false,
            "italic": false,
            "strikethrough": false,
            "text_color": 1,
            "underline": false
          }
        },
        {
          "type": "text_run",
          "content": ", hy vọng tìm ra: thế hệ Agent tiếp theo thay đổi tương lai ngành.",
          "style": {
            "bold": false,
            "inline_code": false,
            "italic": false,
            "strikethrough": false,
            "underline": false
          }
        }
      ]
    },
    {
      "block_id": "doxlgURE4Fr28XwQMNO6b4rB7fg",
      "block_type": 2,
      "block_type_name": "text",
      "elements": [
        {
          "type": "text_run",
          "content": "Cuộc thi lần này hướng tới các nhà phát triển toàn cầu và đội ngũ khởi nghiệp AI để tuyển chọn dự án. Nếu bạn đang phát triển Agent, nếu bạn có một ý tưởng điên rồ nhưng khả thi, nếu bạn đang tìm kiếm cơ hội khởi nghiệp... hãy tham gia sự kiện dành cho những nhà sáng tạo Agent cấp ngành! Hãy trở thành người định nghĩa ngành tiếp theo!",
          "style": {
            "bold": false,
            "inline_code": false,
            "italic": false,
            "strikethrough": false,
            "underline": false
          }
        }
      ]
    },
    {
      "block_id": "doxlgOaIkpre1l6m48MUP3YIT6Y",
      "block_type": 2,
      "block_type_name": "text",
      "elements": [
        {
          "type": "text_run",
          "content": "Agent cấp ngành là gì?",
          "style": {
            "background_color": 8,
            "bold": true,
            "inline_code": false,
            "italic": false,
            "strikethrough": false,
            "text_color": 7,
            "underline": false
          }
        }
      ]
    },
    {
      "block_id": "doxlgQRWPlPlX2lqDLK4tWQFuof",
      "block_type": 2,
      "block_type_name": "text",
      "elements": [
        {
          "type": "text_run",
          "content": "Ví dụ đơn giản:",
          "style": {
            "bold": false,
            "inline_code": false,
            "italic": false,
            "strikethrough": false,
            "underline": false
          }
        }
      ]
    },
    {
      "block_id": "doxlgHZqAfcd1yGQL1U7Maw3yHh",
      "block_type": 2,
      "block_type_name": "text",
      "elements": [
        {
          "type": "text_run",
          "content": "Nếu ai đó tạo ra một \"trợ lý quản lý thời gian hình tôm hùm\", đó chỉ là một ứng dụng AI thú vị.",
          "style": {
            "bold": false,
            "inline_code": false,
            "italic": false,
            "strikethrough": false,
            "underline": false
          }
        }
      ]
    },
    {
      "block_id": "doxlgCwRIDKCPI0z9XYmtBGGWtg",
      "block_type": 2,
      "block_type_name": "text",
      "elements": [
        {
          "type": "text_run",
          "content": "Nhưng nếu trên cơ sở đó nâng cấp thành:",
          "style": {
            "bold": false,
            "inline_code": false,
            "italic": false,
            "strikethrough": false,
            "underline": false
          }
        }
      ]
    },
    {
      "block_id": "doxlgbAyRCsQmqS41sz46C7ym7c",
      "block_type": 12,
      "block_type_name": "bullet",
      "elements": [
        {
          "type": "text_run",
          "content": "Trợ lý quản lý sức khỏe AI hướng tới ngành y tế",
          "style": {
            "bold": false,
            "inline_code": false,
            "italic": false,
            "strikethrough": false,
            "underline": false
          }
        }
      ]
    },
    {
      "block_id": "doxlgjR7T3i0l47nDLsY8Rv1uZe",
      "block_type": 12,
      "block_type_name": "bullet",
      "elements": [
        {
          "type": "text_run",
          "content": "Agent quản lý sức khỏe nhân viên hướng tới doanh nghiệp",
          "style": {
            "bold": false,
            "inline_code": false,
            "italic": false,
            "strikethrough": false,
            "underline": false
          }
        }
      ]
    },
    {
      "block_id": "doxlgPp8Fpq5aRDRUScotVq77Ie",
      "block_type": 12,
      "block_type_name": "bullet",
      "elements": [
        {
          "type": "text_run",
          "content": "Agent theo dõi bệnh nhân hướng tới cơ sở y tế",
          "style": {
            "bold": false,
            "inline_code": false,
            "italic": false,
            "strikethrough": false,
            "underline": false
          }
        }
      ]
    },
    {
      "block_id": "doxlg7QQMAJ13BiPMXk0RpbQ0xf",
      "block_type": 2,
      "block_type_name": "text",
      "elements": [
        {
          "type": "text_run",
          "content": "Khi đó, nó chuyển từ một công cụ giải trí thành: một Agent thực sự có thể đi vào ngành, tạo ra giá trị thương mại.",
          "style": {
            "bold": false,
            "inline_code": false,
            "italic": false,
            "strikethrough": false,
            "underline": false
          }
        }
      ]
    },
    {
      "block_id": "doxlgNwOaZB731WmSh2NXncMEVh",
      "block_type": 2,
      "block_type_name": "text",
      "elements": [
        {
          "type": "text_run",
          "content": "Loại sản phẩm có thể phục vụ ngành, giải quyết vấn đề thực tế, có tiềm năng thương mại hóa — đó chính là Agent cấp ngành mà chúng tôi đang tìm kiếm.",
          "style": {
            "bold": false,
            "inline_code": false,
            "italic": false,
            "strikethrough": false,
            "underline": false
          }
        }
      ]
    },
    {
      "block_id": "doxlgx8FrnOUDkrQu1fiWb2jQig",
      "block_type": 2,
      "block_type_name": "text",
      "elements": [
        {
          "type": "text_run",
          "content": "Ai có thể tham gia?",
          "style": {
            "background_color": 8,
            "bold": true,
            "inline_code": false,
            "italic": false,
            "strikethrough": false,
            "text_color": 7,
            "underline": false
          }
        }
      ]
    },
    {
      "block_id": "doxlgHeXp3npkFo7eMcJwIVmI3b",
      "block_type": 2,
      "block_type_name": "text",
      "elements": [
        {
          "type": "text_run",
          "content": "Dù là nhà phát triển cá nhân, đội nhỏ 2-5 người, hay dự án AI đang khởi nghiệp, đều có thể tham gia. Chỉ cần bạn đang làm AI Agent, bạn có thể đăng ký.",
          "style": {
            "bold": false,
            "inline_code": false,
            "italic": false,
            "strikethrough": false,
            "underline": false
          }
        }
      ]
    },
    {
      "block_id": "doxlgMYtnyRuIYCDzuxzN4lJi9d",
      "block_type": 2,
      "block_type_name": "text",
      "elements": [
        {
          "type": "text_run",
          "content": "Chúng tôi chào đón:",
          "style": {
            "bold": false,
            "inline_code": false,
            "italic": false,
            "strikethrough": false,
            "underline": false
          }
        }
      ]
    },
    {
      "block_id": "doxlgyDuj2mVe7xNbjcWLeB58zT",
      "block_type": 2,
      "block_type_name": "text",
      "elements": [
        {
          "type": "text_run",
          "content": "Nhà phát triển AI Agent ",
          "style": {
            "bold": true,
            "inline_code": false,
            "italic": false,
            "strikethrough": false,
            "underline": false
          }
        },
        {
          "type": "text_run",
          "content": ", bao gồm: nhà phát triển độc lập, geek công nghệ, người yêu thích AI.",
          "style": {
            "bold": false,
            "inline_code": false,
            "italic": false,
            "strikethrough": false,
            "underline": false
          }
        }
      ]
    },
    {
      "block_id": "doxlglr0OVtF2clqtiUnLQ8BgGd",
      "block_type": 2,
      "block_type_name": "text",
      "elements": [
        {
          "type": "text_run",
          "content": "Đội ngũ đổi mới sáng tạo AI ",
          "style": {
            "bold": true,
            "inline_code": false,
            "italic": false,
            "strikethrough": false,
            "underline": false
          }
        },
        {
          "type": "text_run",
          "content": ", bao gồm: đội khởi nghiệp AI, đội kỹ thuật, dự án phòng thí nghiệm.",
          "style": {
            "bold": false,
            "inline_code": false,
            "italic": false,
            "strikethrough": false,
            "underline": false
          }
        }
      ]
    },
    {
      "block_id": "doxlgcdZ6Z5nHXOqOKS6PAJr9QR",
      "block_type": 2,
      "block_type_name": "text",
      "elements": [
        {
          "type": "text_run",
          "content": "Dự án sản phẩm Agent ",
          "style": {
            "bold": true,
            "inline_code": false,
            "italic": false,
            "strikethrough": false,
            "underline": false
          }
        },
        {
          "type": "text_run",
          "content": ", bao gồm: sản phẩm đã ra mắt, dự án Demo, sản phẩm thử nghiệm.",
          "style": {
            "bold": false,
            "inline_code": false,
            "italic": false,
            "strikethrough": false,
            "underline": false
          }
        }
      ]
    },
    {
      "block_id": "doxlgUbubhLqbZctqM4MPvM0zwb",
      "block_type": 2,
      "block_type_name": "text",
      "elements": [
        {
          "type": "text_run",
          "content": "Có những hạng mục thi nào?",
          "style": {
            "background_color": 8,
            "bold": true,
            "inline_code": false,
            "italic": false,
            "strikethrough": false,
            "text_color": 7,
            "underline": false
          }
        }
      ]
    },
    {
      "block_id": "doxlg6Ki5C010DJbFmMLJ6Ztrvc",
      "block_type": 2,
      "block_type_name": "text",
      "elements": [
        {
          "type": "text_run",
          "content": "Sự kiện lần này tập trung vào các kịch bản ứng dụng thực tế của AI Agent cấp ngành, hướng trọng tâm vào 4 hạng mục lớn: Sản xuất thông minh, Logistics thông minh, Thương mại điện tử số trí tuệ và Sức khỏe sinh mệnh.",
          "style": {
            "bold": false,
            "inline_code": false,
            "italic": false,
            "strikethrough": false,
            "underline": false
          }
        }
      ]
    },
    {
      "block_id": "doxlglqBZ0jDCFWhOGRNzk1FdWb",
      "block_type": 2,
      "block_type_name": "text",
      "elements": [
        {
          "type": "text_run",
          "content": "Các lĩnh vực này đang ở giai đoạn then chốt của việc nâng cấp số hóa và trí tuệ hóa. Trong các khâu như quản lý sản xuất, phối hợp chuỗi cung ứng, vận hành thương mại điện tử và dịch vụ y tế, nhu cầu về ra quyết định thông minh và hợp tác tự động hóa không ngừng tăng. Chúng tôi hy vọng phát hiện những ứng dụng AI Agent cấp ngành thực sự có thể đi vào quy trình công nghiệp, giải quyết vấn đề thực tế và có tiềm năng thương mại.",
          "style": {
            "bold": false,
            "inline_code": false,
            "italic": false,
            "strikethrough": false,
            "underline": false
          }
        }
      ]
    },
    {
      "block_id": "doxlgSUYIRnVyZukM6qXEwJwbbf",
      "block_type": 2,
      "block_type_name": "text",
      "elements": [
        {
          "type": "text_run",
          "content": "Hệ thống đánh giá cuộc thi?",
          "style": {
            "background_color": 8,
            "bold": true,
            "inline_code": false,
            "italic": false,
            "strikethrough": false,
            "text_color": 7,
            "underline": false
          }
        }
      ]
    },
    {
      "block_id": "doxlgxUFGrSANdAJlQPsHYHDSuf",
      "block_type": 2,
      "block_type_name": "text",
      "elements": [
        {
          "type": "text_run",
          "content": "01",
          "style": {
            "background_color": 8,
            "bold": false,
            "inline_code": false,
            "italic": false,
            "strikethrough": false,
            "text_color": 7,
            "underline": false
          }
        },
        {
          "type": "text_run",
          "content": "Tính an toàn của Agent là chiều đánh giá quan trọng",
          "style": {
            "bold": false,
            "inline_code": false,
            "italic": false,
            "strikethrough": false,
            "underline": false
          }
        }
      ]
    },
    {
      "block_id": "doxlglVylDmboKq7NbZvA0kUUag",
      "block_type": 2,
      "block_type_name": "text",
      "elements": [
        {
          "type": "text_run",
          "content": "Agent không chỉ là một công cụ, nó có thể: gọi hệ thống bên ngoài, truy cập dữ liệu, tự động thực thi tác vụ, ảnh hưởng đến quy trình kinh doanh thực tế",
          "style": {
            "bold": false,
            "inline_code": false,
            "italic": false,
            "strikethrough": false,
            "underline": false
          }
        }
      ]
    },
    {
      "block_id": "doxlgsfgnwrDr4OWzP3MQZpUDrb",
      "block_type": 2,
      "block_type_name": "text",
      "elements": [
        {
          "type": "text_run",
          "content": "Do đó, thiết kế an toàn là tiền đề để Agent có thể đi vào ngành.",
          "style": {
            "bold": false,
            "inline_code": false,
            "italic": false,
            "strikethrough": false,
            "underline": false
          }
        }
      ]
    },
    {
      "block_id": "doxlgwJn2UF06DsA6mf8HBYbLPe",
      "block_type": 2,
      "block_type_name": "text",
      "elements": [
        {
          "type": "text_run",
          "content": "Linh Hạch Số Trí khi đánh giá dự án sẽ đặc biệt chú ý:",
          "style": {
            "bold": false,
            "inline_code": false,
            "italic": false,
            "strikethrough": false,
            "underline": false
          }
        }
      ]
    },
    {
      "block_id": "doxlgDZgzKDvw5Wxk6Y8OW0rYqc",
      "block_type": 12,
      "block_type_name": "bullet",
      "elements": [
        {
          "type": "text_run",
          "content": "Có tránh được rủi ro mã độc không",
          "style": {
            "bold": false,
            "inline_code": false,
            "italic": false,
            "strikethrough": false,
            "underline": false
          }
        }
      ]
    },
    {
      "block_id": "doxlg5vOeShgnD36fvKeB4lZMll",
      "block_type": 12,
      "block_type_name": "bullet",
      "elements": [
        {
          "type": "text_run",
          "content": "Có nhận thức cơ bản về bảo mật dữ liệu không",
          "style": {
            "bold": false,
            "inline_code": false,
            "italic": false,
            "strikethrough": false,
            "underline": false
          }
        }
      ]
    },
    {
      "block_id": "doxlgumU7mOxARYpdpBYfK5Uhrb",
      "block_type": 12,
      "block_type_name": "bullet",
      "elements": [
        {
          "type": "text_run",
          "content": "Có tránh được rò rỉ thông tin nhạy cảm không",
          "style": {
            "bold": false,
            "inline_code": false,
            "italic": false,
            "strikethrough": false,
            "underline": false
          }
        }
      ]
    },
    {
      "block_id": "doxlgTohDXUCBipd21avZ9hJvqg",
      "block_type": 12,
      "block_type_name": "bullet",
      "elements": [
        {
          "type": "text_run",
          "content": "Có kiểm soát quyền hệ thống hợp lý không",
          "style": {
            "bold": false,
            "inline_code": false,
            "italic": false,
            "strikethrough": false,
            "underline": false
          }
        }
      ]
    },
    {
      "block_id": "doxlgfQf7KR6YpkukFteBco04xd",
      "block_type": 12,
      "block_type_name": "bullet",
      "elements": [
        {
          "type": "text_run",
          "content": "Có tránh tạo nội dung không phù hợp hoặc vi phạm không",
          "style": {
            "bold": false,
            "inline_code": false,
            "italic": false,
            "strikethrough": false,
            "underline": false
          }
        }
      ]
    },
    {
      "block_id": "doxlg30x5cgaIM6plE1TBAeYysb",
      "block_type": 2,
      "block_type_name": "text",
      "elements": [
        {
          "type": "text_run",
          "content": "Một Agent thực sự có thể đi vào ngành không chỉ cần thông minh, mà còn phải an toàn, đáng tin cậy, có thể kiểm soát. Tất cả thí sinh vui lòng tự kiểm tra an toàn trước khi nộp dự án. Có thể tham khảo tài liệu gần đây do Bộ Công nghiệp và Công nghệ Thông tin phát hành ",
          "style": {
            "bold": false,
            "inline_code": false,
            "italic": false,
            "strikethrough": false,
            "underline": false
          }
        },
        {
          "type": "text_run",
          "content": "《6 điều nên và 6 điều không nên khi sử dụng \"Tôm hùm\"》",
          "style": {
            "bold": false,
            "inline_code": false,
            "italic": false,
            "link": {
              "url": "https%3A%2F%2Fmp.weixin.qq.com%2Fs%3F__biz%3DMzA4NDI3NjcyNA%3D%3D%26mid%3D2650203502%26idx%3D1%26sn%3D70953cf838e642db6118c8b3a935f0c8%26scene%3D21%23wechat_redirect"
            },
            "strikethrough": false,
            "underline": false
          }
        }
      ]
    },
    {
      "block_id": "doxlgFKki0U9vNzehf0ZUx82hhh",
      "block_type": 2,
      "block_type_name": "text",
      "elements": [
        {
          "type": "text_run",
          "content": "02",
          "style": {
            "background_color": 8,
            "bold": false,
            "inline_code": false,
            "italic": false,
            "strikethrough": false,
            "text_color": 7,
            "underline": false
          }
        },
        {
          "type": "text_run",
          "content": "Tiêu chuẩn tham khảo chấm điểm của ban giám khảo",
          "style": {
            "bold": false,
            "inline_code": false,
            "italic": false,
            "strikethrough": false,
            "underline": false
          }
        }
      ]
    },
    {
      "block_id": "doxlgt6xeyVrocasJCW5o2HC1wh",
      "block_type": 2,
      "block_type_name": "text",
      "elements": [
        {
          "type": "text_run",
          "content": "Trong vòng chung kết, ban giám khảo sẽ chấm điểm theo 5 chiều sau:",
          "style": {
            "bold": false,
            "inline_code": false,
            "italic": false,
            "strikethrough": false,
            "underline": false
          }
        }
      ]
    },
    {
      "block_id": "doxlgZbFfKC6YNCGTrLuOwLcund",
      "block_type": 2,
      "block_type_name": "text",
      "elements": [
        {
          "type": "text_run",
          "content": "Tính an toàn: Có thiết kế an toàn và tuân thủ cơ bản không",
          "style": {
            "bold": false,
            "inline_code": false,
            "italic": false,
            "strikethrough": false,
            "underline": false
          }
        }
      ]
    },
    {
      "block_id": "doxlghhAfRP9LEaQ7schCvygrQd",
      "block_type": 2,
      "block_type_name": "text",
      "elements": [
        {
          "type": "text_run",
          "content": "Mức độ hoàn thiện: Chức năng có đầy đủ không, trải nghiệm người dùng có mượt mà không",
          "style": {
            "bold": false,
            "inline_code": false,
            "italic": false,
            "strikethrough": false,
            "underline": false
          }
        }
      ]
    },
    {
      "block_id": "doxlgGy4vDNmwsV2blhx4GbrjZf",
      "block_type": 2,
      "block_type_name": "text",
      "elements": [
        {
          "type": "text_run",
          "content": "Giá trị ứng dụng: Có thực sự giải quyết vấn đề ngành không",
          "style": {
            "bold": false,
            "inline_code": false,
            "italic": false,
            "strikethrough": false,
            "underline": false
          }
        }
      ]
    },
    {
      "block_id": "doxlgrEwpIJvIEQDs0QIzh6LLzd",
      "block_type": 2,
      "block_type_name": "text",
      "elements": [
        {
          "type": "text_run",
          "content": "Tiềm năng thương mại: Có cơ hội công nghiệp hóa hoặc thị trường không",
          "style": {
            "bold": false,
            "inline_code": false,
            "italic": false,
            "strikethrough": false,
            "underline": false
          }
        }
      ]
    },
    {
      "block_id": "doxlgs0iuc5F0I4sNBekaweIWcd",
      "block_type": 2,
      "block_type_name": "text",
      "elements": [
        {
          "type": "text_run",
          "content": "Tính đổi mới: Công nghệ hoặc mô hình sản phẩm có tính đột phá không",
          "style": {
            "bold": false,
            "inline_code": false,
            "italic": false,
            "strikethrough": false,
            "underline": false
          }
        }
      ]
    },
    {
      "block_id": "doxlg9nOr4RxOTb7BTho2M2cLjg",
      "block_type": 2,
      "block_type_name": "text",
      "elements": [
        {
          "type": "text_run",
          "content": "Giải thưởng trị giá ",
          "style": {
            "bold": false,
            "inline_code": false,
            "italic": false,
            "strikethrough": false,
            "underline": false
          }
        },
        {
          "type": "text_run",
          "content": "500.000 NDT ",
          "style": {
            "bold": false,
            "inline_code": false,
            "italic": false,
            "strikethrough": false,
            "text_color": 1,
            "underline": false
          }
        },
        {
          "type": "text_run",
          "content": "đang chờ bạn nhận!",
          "style": {
            "bold": false,
            "inline_code": false,
            "italic": false,
            "strikethrough": false,
            "underline": false
          }
        }
      ]
    },
    {
      "block_id": "doxlgTFynh8cdSsWIMiO7oY9zWc",
      "block_type": 2,
      "block_type_name": "text",
      "elements": [
        {
          "type": "text_run",
          "content": "01",
          "style": {
            "background_color": 8,
            "bold": false,
            "inline_code": false,
            "italic": false,
            "strikethrough": false,
            "text_color": 7,
            "underline": false
          }
        },
        {
          "type": "text_run",
          "content": "Tổng giải thưởng cuộc thi lên tới 140.000 NDT!",
          "style": {
            "bold": false,
            "inline_code": false,
            "italic": false,
            "strikethrough": false,
            "underline": false
          }
        }
      ]
    },
    {
      "block_id": "doxlgnHn7V94G1RUeYeqmUp5HWb",
      "block_type": 2,
      "block_type_name": "text",
      "elements": [
        {
          "type": "text_run",
          "content": "Trong đó:",
          "style": {
            "bold": false,
            "inline_code": false,
            "italic": false,
            "strikethrough": false,
            "underline": false
          }
        }
      ]
    },
    {
      "block_id": "doxlgY0N3VAVWvZdn70qKqD59jy",
      "block_type": 2,
      "block_type_name": "text",
      "elements": [
        {
          "type": "text_run",
          "content": "Giải nhất 1 người — Thưởng 50.000 NDT",
          "style": {
            "bold": true,
            "inline_code": false,
            "italic": false,
            "strikethrough": false,
            "text_color": 1,
            "underline": false
          }
        }
      ]
    },
    {
      "block_id": "doxlg1CpEXaAiS49sR4ZJxUbRlw",
      "block_type": 2,
      "block_type_name": "text",
      "elements": [
        {
          "type": "text_run",
          "content": "Giải nhì 2 người — Thưởng 30.000 NDT",
          "style": {
            "bold": true,
            "inline_code": false,
            "italic": false,
            "strikethrough": false,
            "text_color": 1,
            "underline": false
          }
        }
      ]
    },
    {
      "block_id": "doxlgu3uRB6tSgv0HrpD78z4x0d",
      "block_type": 2,
      "block_type_name": "text",
      "elements": [
        {
          "type": "text_run",
          "content": "Giải ba 3 người — Thưởng 10.000 NDT",
          "style": {
            "bold": true,
            "inline_code": false,
            "italic": false,
            "strikethrough": false,
            "text_color": 1,
            "underline": false
          }
        }
      ]
    },
    {
      "block_id": "doxlg6oPfcVMkXMy3COvNUYbvvh",
      "block_type": 2,
      "block_type_name": "text",
      "elements": [
        {
          "type": "text_run",
          "content": "Giải Ưu tú nhiều suất, thưởng giá ưu đãi Token Qianwen, token miễn phí nền tảng Bách Luyện, dùng thử miễn phí server 1 tháng! Còn rất nhiều phúc lợi đang được mở khóa...",
          "style": {
            "bold": false,
            "inline_code": false,
            "italic": false,
            "strikethrough": false,
            "underline": false
          }
        }
      ]
    },
    {
      "block_id": "doxlgxnmvLR43YvtZ24hWbH1VKg",
      "block_type": 2,
      "block_type_name": "text",
      "elements": [
        {
          "type": "text_run",
          "content": "02",
          "style": {
            "background_color": 8,
            "bold": false,
            "inline_code": false,
            "italic": false,
            "strikethrough": false,
            "text_color": 7,
            "underline": false
          }
        },
        {
          "type": "text_run",
          "content": "Chỗ ngồi OPC, dịch vụ khoa học sáng tạo và kết nối ngành trọn gói!",
          "style": {
            "bold": false,
            "inline_code": false,
            "italic": false,
            "strikethrough": false,
            "underline": false
          }
        }
      ]
    },
    {
      "block_id": "doxlgmuNictK26kGxw0MA8dEqkc",
      "block_type": 2,
      "block_type_name": "text",
      "elements": [
        {
          "type": "text_run",
          "content": "Các đội đoạt giải Nhất, Nhì, Ba sẽ được hưởng quyền lợi nhập trú độc quyền tại Xưởng Mơ Bắc Cao Phong, Hàng Châu: cung cấp miễn phí chỗ ngồi văn phòng OPC sẵn sàng sử dụng, mở khóa phúc lợi miễn phí toàn bộ tiện ích cơ bản như mặt bằng, mạng, thiết bị văn phòng; dịch vụ khoa học sáng tạo trọn gói bao gồm đăng ký kinh doanh miễn phí, kết nối tài nguyên chuỗi công nghiệp, kết nối đầu tư - tài chính, hướng dẫn xin chính sách hỗ trợ toàn diện, giúp các dự án AI Agent chất lượng nhanh chóng hiện thực hóa ứng dụng công nghệ và chuyển đổi thương mại, để đội khởi nghiệp nhẹ gánh lên đường, tăng tốc phát triển.",
          "style": {
            "bold": false,
            "inline_code": false,
            "italic": false,
            "strikethrough": false,
            "underline": false
          }
        }
      ]
    },
    {
      "block_id": "doxlgsS3h6PYIS7rVzDDd65Xc2b",
      "block_type": 2,
      "block_type_name": "text",
      "elements": [
        {
          "type": "text_run",
          "content": "03",
          "style": {
            "background_color": 8,
            "bold": false,
            "inline_code": false,
            "italic": false,
            "strikethrough": false,
            "text_color": 7,
            "underline": false
          }
        },
        {
          "type": "text_run",
          "content": "Ngoài ra, bạn còn có thể:",
          "style": {
            "bold": false,
            "inline_code": false,
            "italic": false,
            "strikethrough": false,
            "underline": false
          }
        }
      ]
    },
    {
      "block_id": "doxlg6hGmeqSCE7zPDPQ6hHxAKg",
      "block_type": 12,
      "block_type_name": "bullet",
      "elements": [
        {
          "type": "text_run",
          "content": "Đối mặt trực tiếp với các nhà đầu tư và doanh nhân hàng đầu, mạnh dạn trình bày ý tưởng mới, để những người thực sự hiểu AI lắng nghe ý tưởng khởi nghiệp của bạn;",
          "style": {
            "bold": false,
            "inline_code": false,
            "italic": false,
            "strikethrough": false,
            "underline": false
          }
        }
      ]
    },
    {
      "block_id": "doxlgS7NUdoVTWqBAZ8gCkLKApf",
      "block_type": 12,
      "block_type_name": "bullet",
      "elements": [
        {
          "type": "text_run",
          "content": "Kết nối với đội ngũ dịch vụ công nghiệp mạnh nhất Hàng Châu, biến ý tưởng thành dự án, đưa dự án vào ngành;",
          "style": {
            "bold": false,
            "inline_code": false,
            "italic": false,
            "strikethrough": false,
            "underline": false
          }
        }
      ]
    },
    {
      "block_id": "doxlgEqmIP9t0b2E0Ph4o3GaAry",
      "block_type": 12,
      "block_type_name": "bullet",
      "elements": [
        {
          "type": "text_run",
          "content": "Tham gia cộng đồng nhà phát triển AI hot nhất hiện nay, giao lưu cùng các cao thủ công nghệ, nhà khởi nghiệp, chuyên gia tài nguyên, cùng nhau phát triển lớn mạnh trong sự va chạm ý tưởng.",
          "style": {
            "bold": false,
            "inline_code": false,
            "italic": false,
            "strikethrough": false,
            "underline": false
          }
        }
      ]
    },
    {
      "block_id": "doxlgvnMshdnvB4t76ihDicdAwe",
      "block_type": 2,
      "block_type_name": "text",
      "elements": [
        {
          "type": "text_run",
          "content": "Cách tham gia như sau, nhanh chóng đăng ký ngay!",
          "style": {
            "bold": false,
            "inline_code": false,
            "italic": false,
            "strikethrough": false,
            "text_color": 1,
            "underline": false
          }
        }
      ]
    },
    {
      "block_id": "doxlg1DVRrurv5abOBCtoXlIhZf",
      "block_type": 2,
      "block_type_name": "text",
      "elements": [
        {
          "type": "text_run",
          "content": "Thời gian tuyển chọn dự án",
          "style": {
            "background_color": 8,
            "bold": true,
            "inline_code": false,
            "italic": false,
            "strikethrough": false,
            "text_color": 7,
            "underline": false
          }
        }
      ]
    },
    {
      "block_id": "doxlgsPl5ZQdqwSzboFag7Si3sd",
      "block_type": 2,
      "block_type_name": "text",
      "elements": [
        {
          "type": "text_run",
          "content": "Từ nay — 25/03/2026 17:00",
          "style": {
            "bold": false,
            "inline_code": false,
            "italic": false,
            "strikethrough": false,
            "underline": false
          }
        }
      ]
    },
    {
      "block_id": "doxlgUdxHSVsswrKzDkRxfOvdVd",
      "block_type": 2,
      "block_type_name": "text",
      "elements": [
        {
          "type": "text_run",
          "content": "Nếu bạn đã có Demo dự án Agent hoàn chỉnh, hãy nộp ngay qua mã QR bên dưới!",
          "style": {
            "bold": false,
            "inline_code": false,
            "italic": false,
            "strikethrough": false,
            "underline": false
          }
        }
      ]
    },
    {
      "block_id": "doxlgoy0C3b9K1fr2aNnaCoeIth",
      "block_type": 2,
      "block_type_name": "text",
      "elements": [
        {
          "type": "text_run",
          "content": "(Cổng đăng ký hoạt động chính thức và tuyển chọn dự án)",
          "style": {
            "bold": false,
            "inline_code": false,
            "italic": false,
            "strikethrough": false,
            "text_color": 1,
            "underline": false
          }
        }
      ]
    },
    {
      "block_id": "doxlgnymsrfAsPqO61XtZ34ngCg",
      "block_type": 2,
      "block_type_name": "text",
      "elements": [
        {
          "type": "text_run",
          "content": "Nếu bạn chưa có Demo hoàn chỉnh, có thể đăng ký trước qua mã QR phía trên, sau đó tham gia nhóm trao đổi hoạt động để liên hệ trợ lý sự kiện!",
          "style": {
            "bold": false,
            "inline_code": false,
            "italic": false,
            "strikethrough": false,
            "underline": false
          }
        }
      ]
    },
    {
      "block_id": "doxlgA9ZJKdaJq1KztJ71DSaNdH",
      "block_type": 2,
      "block_type_name": "text",
      "elements": [
        {
          "type": "text_run",
          "content": "(Tham gia cộng đồng trao đổi hoạt động chính thức trên Feishu,",
          "style": {
            "bold": false,
            "inline_code": false,
            "italic": false,
            "strikethrough": false,
            "text_color": 1,
            "underline": false
          }
        }
      ]
    },
    {
      "block_id": "doxlgPj1DCnzUJfbEzXrhNtquvd",
      "block_type": 2,
      "block_type_name": "text",
      "elements": [
        {
          "type": "text_run",
          "content": "theo dõi tiến trình hoạt động, thông tin lọt vào vòng trong và trao đổi học hỏi)",
          "style": {
            "bold": false,
            "inline_code": false,
            "italic": false,
            "strikethrough": false,
            "text_color": 1,
            "underline": false
          }
        }
      ]
    },
    {
      "block_id": "doxlgkqOZiTH1oL7DY4IOYnuYge",
      "block_type": 2,
      "block_type_name": "text",
      "elements": [
        {
          "type": "text_run",
          "content": "Thông tin nộp dự án",
          "style": {
            "background_color": 8,
            "bold": true,
            "inline_code": false,
            "italic": false,
            "strikethrough": false,
            "text_color": 7,
            "underline": false
          }
        }
      ]
    },
    {
      "block_id": "doxlguap1elF5ddV6zsdVNkv98e",
      "block_type": 2,
      "block_type_name": "text",
      "elements": [
        {
          "type": "text_run",
          "content": "Quét mã QR đăng ký phía trên để điền biểu mẫu đăng ký.",
          "style": {
            "bold": false,
            "inline_code": false,
            "italic": false,
            "strikethrough": false,
            "underline": false
          }
        }
      ]
    },
    {
      "block_id": "doxlgIKnvQTbbGdS35OwQzNn0he",
      "block_type": 2,
      "block_type_name": "text",
      "elements": [
        {
          "type": "text_run",
          "content": "Thông tin cần nộp chủ yếu bao gồm:",
          "style": {
            "bold": false,
            "inline_code": false,
            "italic": false,
            "strikethrough": false,
            "underline": false
          }
        }
      ]
    },
    {
      "block_id": "doxlgyboCxvKKHqHpJuydmhz7sM",
      "block_type": 12,
      "block_type_name": "bullet",
      "elements": [
        {
          "type": "text_run",
          "content": "Thông tin cơ bản và giới thiệu thí sinh/đội thi",
          "style": {
            "bold": false,
            "inline_code": false,
            "italic": false,
            "strikethrough": false,
            "underline": false
          }
        }
      ]
    },
    {
      "block_id": "doxlgxDMv9OWJ3BThxZ7xrQbZ3d",
      "block_type": 12,
      "block_type_name": "bullet",
      "elements": [
        {
          "type": "text_run",
          "content": "Tên dự án và giới thiệu tóm tắt dự án",
          "style": {
            "bold": false,
            "inline_code": false,
            "italic": false,
            "strikethrough": false,
            "underline": false
          }
        }
      ]
    },
    {
      "block_id": "doxlgFVZeQ0EoTPchwRjlW5f5Ee",
      "block_type": 12,
      "block_type_name": "bullet",
      "elements": [
        {
          "type": "text_run",
          "content": "Ảnh chụp màn hình Demo dự án hoặc video trình diễn (Lưu ý: Demo cần là liên kết công khai có thể truy cập, không được chứa chương trình độc hại hoặc nội dung vi phạm, nếu không sẽ bị xóa thông tin đăng ký, coi như đăng ký thất bại)",
          "style": {
            "bold": false,
            "inline_code": false,
            "italic": false,
            "strikethrough": false,
            "underline": false
          }
        }
      ]
    },
    {
      "block_id": "doxlg9C6LssZNGP24njIG6xlkDr",
      "block_type": 2,
      "block_type_name": "text",
      "elements": [
        {
          "type": "text_run",
          "content": "Lưu ý: Nếu ý tưởng của bạn chưa thành Demo, hãy tranh thủ thời gian và vào nhóm hoạt động liên hệ trợ lý!",
          "style": {
            "bold": true,
            "inline_code": false,
            "italic": false,
            "strikethrough": false,
            "underline": false
          }
        }
      ]
    },
    {
      "block_id": "doxlgDPruyfbfLVWEcAL99OjPNg",
      "block_type": 2,
      "block_type_name": "text",
      "elements": [
        {
          "type": "text_run",
          "content": "Ban tổ chức chính thức sẽ xét duyệt tất cả dự án và đưa vào quy trình bình chọn. Nếu dự án của bạn lọt vào vòng chung kết offline, chúng tôi sẽ liên hệ bạn trước 3-5 ngày. Vui lòng điền số điện thoại thật và giữ điện thoại thông suốt.",
          "style": {
            "bold": false,
            "inline_code": false,
            "italic": false,
            "strikethrough": false,
            "underline": false
          }
        }
      ]
    },
    {
      "block_id": "doxlg0kp5W5N26IROBQZyBjP9Vb",
      "block_type": 2,
      "block_type_name": "text",
      "elements": [
        {
          "type": "text_run",
          "content": "Quy trình bình chọn dự án và vòng chung kết offline",
          "style": {
            "bold": false,
            "inline_code": false,
            "italic": false,
            "strikethrough": false,
            "underline": false
          }
        }
      ]
    },
    {
      "block_id": "doxlgySNtIrnAmzLfyOYwIQc56e",
      "block_type": 2,
      "block_type_name": "text",
      "elements": [
        {
          "type": "text_run",
          "content": "Vòng sơ tuyển dự án trực tuyến",
          "style": {
            "background_color": 8,
            "bold": true,
            "inline_code": false,
            "italic": false,
            "strikethrough": false,
            "text_color": 7,
            "underline": false
          }
        }
      ]
    },
    {
      "block_id": "doxlgXlFdBizxONKH7DtGSPXMPc",
      "block_type": 2,
      "block_type_name": "text",
      "elements": [
        {
          "type": "text_run",
          "content": "Thời gian: 26/03/2026 — 01/04/2026",
          "style": {
            "bold": false,
            "inline_code": false,
            "italic": false,
            "strikethrough": false,
            "underline": false
          }
        }
      ]
    },
    {
      "block_id": "doxlgTjc8bDakwBlUbKa3K6a53b",
      "block_type": 2,
      "block_type_name": "text",
      "elements": [
        {
          "type": "text_run",
          "content": "Ban đánh giá kỹ thuật chính thức sẽ sàng lọc 20 dự án xuất sắc từ tất cả dự án để vào vòng chung kết offline.",
          "style": {
            "bold": false,
            "inline_code": false,
            "italic": false,
            "strikethrough": false,
            "underline": false
          }
        }
      ]
    },
    {
      "block_id": "doxlgkttgT3Ld6aWULXihIpv2Ke",
      "block_type": 2,
      "block_type_name": "text",
      "elements": [
        {
          "type": "text_run",
          "content": "Tiêu chuẩn sàng lọc bao gồm: an toàn và tuân thủ, kịch bản ứng dụng cấp ngành, đổi mới công nghệ, tiềm năng thương mại, mức độ hoàn thiện thông tin đăng ký, v.v.",
          "style": {
            "bold": false,
            "inline_code": false,
            "italic": false,
            "strikethrough": false,
            "underline": false
          }
        }
      ]
    },
    {
      "block_id": "doxlg4dtzinFd7NuJQZuFowTJXb",
      "block_type": 2,
      "block_type_name": "text",
      "elements": [
        {
          "type": "text_run",
          "content": "Vòng chung kết trình bày offline",
          "style": {
            "background_color": 8,
            "bold": true,
            "inline_code": false,
            "italic": false,
            "strikethrough": false,
            "text_color": 7,
            "underline": false
          }
        }
      ]
    },
    {
      "block_id": "doxlgGQWPZ72d8SPzn4kXNEGSJb",
      "block_type": 2,
      "block_type_name": "text",
      "elements": [
        {
          "type": "text_run",
          "content": "Thời gian: 02/04/2026 9:00—17:30",
          "style": {
            "bold": false,
            "inline_code": false,
            "italic": false,
            "strikethrough": false,
            "underline": false
          }
        }
      ]
    },
    {
      "block_id": "doxlgll57nUFwrjuwLfdqXNtYGd",
      "block_type": 2,
      "block_type_name": "text",
      "elements": [
        {
          "type": "text_run",
          "content": "Địa điểm: Tầng 24, Tòa A, Quảng trường Thời đại Hoa Tinh, Quận Tây Hồ, Hàng Châu, Trung Quốc (Phòng khách Nhà khoa học Bắc Cao Phong)",
          "style": {
            "bold": false,
            "inline_code": false,
            "italic": false,
            "strikethrough": false,
            "underline": false
          }
        }
      ]
    },
    {
      "block_id": "doxlguyw91chiLAEKUoPijr9xze",
      "block_type": 2,
      "block_type_name": "text",
      "elements": [
        {
          "type": "text_run",
          "content": "20 dự án lọt vào vòng trong sẽ trình diễn Demo tại chỗ (Các bạn muốn đến xem thi trực tiếp hãy theo dõi bài đăng tiếp theo trên tài khoản công khai nhé! Chúng tôi sẽ mở kênh đăng ký cho khán giả).",
          "style": {
            "bold": false,
            "inline_code": false,
            "italic": false,
            "strikethrough": false,
            "underline": false
          }
        }
      ]
    },
    {
      "block_id": "doxlgm8mZ0Fv70pbAKKwjflGDTg",
      "block_type": 2,
      "block_type_name": "text",
      "elements": [
        {
          "type": "text_run",
          "content": "Bạn sẽ đối mặt với ban giám khảo gồm 5 vị, bao gồm: chuyên gia công nghệ AI, doanh nhân, nhà đầu tư hàng đầu trong ngành",
          "style": {
            "bold": false,
            "inline_code": false,
            "italic": false,
            "strikethrough": false,
            "underline": false
          }
        }
      ]
    },
    {
      "block_id": "doxlgu05sDeLaOdpXJYeyzTjHUf",
      "block_type": 2,
      "block_type_name": "text",
      "elements": [
        {
          "type": "text_run",
          "content": "Mỗi đội cần:",
          "style": {
            "bold": false,
            "inline_code": false,
            "italic": false,
            "strikethrough": false,
            "underline": false
          }
        }
      ]
    },
    {
      "block_id": "doxlgNtWroVcRoojKwdvzIKayBb",
      "block_type": 12,
      "block_type_name": "bullet",
      "elements": [
        {
          "type": "text_run",
          "content": "Trình diễn Demo sản phẩm tại chỗ (thời lượng 10 phút)",
          "style": {
            "bold": false,
            "inline_code": false,
            "italic": false,
            "strikethrough": false,
            "underline": false
          }
        }
      ]
    },
    {
      "block_id": "doxlgRj63Yhy3wnA72NeroqL1Sh",
      "block_type": 12,
      "block_type_name": "bullet",
      "elements": [
        {
          "type": "text_run",
          "content": "Giới thiệu logic và giá trị dự án (thời lượng 5 phút)",
          "style": {
            "bold": false,
            "inline_code": false,
            "italic": false,
            "strikethrough": false,
            "underline": false
          }
        }
      ]
    },
    {
      "block_id": "doxlgMk8GzoGoCABnK8AJzu9klk",
      "block_type": 2,
      "block_type_name": "text",
      "elements": [
        {
          "type": "text_run",
          "content": "Ban giám khảo sẽ chấm điểm theo quy tắc, cuối cùng bình chọn ra: Giải nhất 1, Giải nhì 2, Giải ba 3 và nhiều Giải Ưu tú.",
          "style": {
            "bold": false,
            "inline_code": false,
            "italic": false,
            "strikethrough": false,
            "underline": false
          }
        }
      ]
    },
    {
      "block_id": "doxlg5nZeF4mF2CCCuoRgToAsec",
      "block_type": 2,
      "block_type_name": "text",
      "elements": [
        {
          "type": "text_run",
          "content": "Tất cả thí sinh chung kết có mặt tại hiện trường còn có cơ hội tham gia hội nghị kín do Linh Hạch Số Trí tổ chức sau đó, gặp mặt trực tiếp nhà đầu tư, tổ chức tài chính, doanh nhân, nhận được hỗ trợ đầu tư mạo hiểm!",
          "style": {
            "bold": false,
            "inline_code": false,
            "italic": false,
            "strikethrough": false,
            "underline": false
          }
        }
      ]
    },
    {
      "block_id": "doxlgNalcNi5DTmqNG3fuIaQczg",
      "block_type": 2,
      "block_type_name": "text",
      "elements": [
        {
          "type": "text_run",
          "content": "Điều quan trọng nhất trong thời đại AI không phải là mô hình, mà là ai có thể dùng Agent tái cấu trúc ngành.",
          "style": {
            "bold": false,
            "inline_code": false,
            "italic": false,
            "strikethrough": false,
            "underline": false
          }
        }
      ]
    },
    {
      "block_id": "doxlgrqNKqvfh83Pw9Vws0uXvFb",
      "block_type": 2,
      "block_type_name": "text",
      "elements": [
        {
          "type": "text_run",
          "content": "Nếu bạn đang phát triển AI Agent, nếu bạn có ý tưởng thay đổi ngành, nếu bạn đang tìm kiếm cơ hội khởi nghiệp AI...",
          "style": {
            "bold": false,
            "inline_code": false,
            "italic": false,
            "strikethrough": false,
            "underline": false
          }
        }
      ]
    },
    {
      "block_id": "doxlg1jpx482DiOxwXnAw1P3VYg",
      "block_type": 2,
      "block_type_name": "text",
      "elements": [
        {
          "type": "text_run",
          "content": "Hãy tham gia: AI Hackathon Tôm Hùm · Đại hội Bình chọn AI Agent cấp ngành!",
          "style": {
            "bold": false,
            "inline_code": false,
            "italic": false,
            "strikethrough": false,
            "text_color": 1,
            "underline": false
          }
        }
      ]
    },
    {
      "block_id": "doxlgx6gLndLaPRI1xpFJWa2erh",
      "block_type": 2,
      "block_type_name": "text",
      "elements": [
        {
          "type": "text_run",
          "content": "Bạn, chính là người định nghĩa ngành tiếp theo!",
          "style": {
            "bold": false,
            "inline_code": false,
            "italic": false,
            "strikethrough": false,
            "text_color": 1,
            "underline": false
          }
        }
      ]
    },
    {
      "block_id": "doxlggfOqzA3dAwREas3ftKmFEY",
      "block_type": 2,
      "block_type_name": "text",
      "elements": [
        {
          "type": "text_run",
          "content": "(Cổng đăng ký, quét mã để điền Demo!)",
          "style": {
            "bold": true,
            "inline_code": false,
            "italic": false,
            "strikethrough": false,
            "text_color": 1,
            "underline": false
          }
        }
      ]
    }
  ]
}